gutils/__init__.py
gutils/__main__.py
gutils/cmdline.py
gutils/demo.py
gutils/ckpt_tr/__init__.py
gutils/ckpt_tr/ckpt_transfer.py
gutils/logger/__init__.py
gutils/logger/logging.py
gutils/tests/__init__.py
gutils/utils/__init__.py
gutils/utils/decorators.py
GauDLutils-0.2.5.dist-info/METADATA
GauDLutils-0.2.5.dist-info/WHEEL
GauDLutils-0.2.5.dist-info/top_level.txt
GauDLutils-0.2.5.dist-info/RECORD
