Metadata-Version: 2.1
Name: GauDLutils
Version: 0.2.5
Summary: tools for deeplearning developing
Home-page: https://github.com/GauthierLi/Gutils
Author: liweikang02
Author-email: lwklxh@163.com
License: MIT
Classifier: Programming Language :: Python
Classifier: Programming Language :: Python :: 3
